README.md
pawabot/__init__.py
pawabot/__main__.py
pawabot/callbacks.py
pawabot/cli.py
pawabot/privileges.py
pawabot/torrents.py
pawabot/utils.py
pyproject.toml
pawabot-0.1.1.dist-info/entry_points.txt
pawabot-0.1.1.dist-info/LICENSE
pawabot-0.1.1.dist-info/WHEEL
pawabot-0.1.1.dist-info/METADATA
pawabot-0.1.1.dist-info/RECORD
