Metadata-Version: 2.1
Name: pawabot
Version: 0.1.1
Summary: A bot for many things: aria2 management, torrent sites crawling, media organization with filebot and plex.
Home-page: https://github.com/pawamoy/pawabot
Keywords: telegram-bot,aria2
Author: Timothée Mazzucotelli
Author-email: pawamoy@pm.me
Requires-Python: >=3.6,<4.0
Classifier: Programming Language :: Python :: 3
Classifier: Programming Language :: Python :: 3.6
Classifier: Programming Language :: Python :: 3.7
Requires-Dist: aria2p (>=0.6.0,<0.7.0)
Requires-Dist: beautifulsoup4 (>=4.8,<5.0)
Requires-Dist: loguru (>=0.3.2,<0.4.0)
Requires-Dist: privibot (>=0.1.0,<0.2.0)
Requires-Dist: python-telegram-bot (==12.0.0b1)
Requires-Dist: requests (>=2.22,<3.0)
Requires-Dist: sqlalchemy (>=1.3,<2.0)
Requires-Dist: tomlkit (>=0.5.5,<0.6.0)
Requires-Dist: xdg (>=4.0,<5.0)
Project-URL: Repository, https://github.com/pawamoy/pawabot
